nbmultitask.py
setup.cfg
setup.py
nbmultitask.egg-info/PKG-INFO
nbmultitask.egg-info/SOURCES.txt
nbmultitask.egg-info/dependency_links.txt
nbmultitask.egg-info/top_level.txt