Metadata-Version: 1.1
Name: nbmultitask
Version: 0.1.0
Summary: ipywidget controls for multitasking in Jupyter notebooks
Home-page: https://github.com/micahscopes/nbmultitask
Author: Micah Fitch
Author-email: micahscopes@gmail.com
License: MIT
Download-URL: https://github.com/micahscopes/nbmultitask/archive/0.1.0.tar.gz
Platform: UNKNOWN
Classifier: Programming Language :: Python
Classifier: Programming Language :: Python :: 3.6
